svo_api/__init__.py
svo_api/_version.py
svo_api/svo.py
svo_api-0.1.1.dist-info/LICENSE
svo_api-0.1.1.dist-info/METADATA
svo_api-0.1.1.dist-info/WHEEL
svo_api-0.1.1.dist-info/top_level.txt
svo_api-0.1.1.dist-info/RECORD
