Metadata-Version: 2.1
Name: svo-api
Version: 0.1.1
Summary: API to download SVO filters
Home-page: https://github.com/temuller/svo_api
Author: Tomás Enrique Müller-Bravo
Author-email: t.e.muller-bravo@ice.csic.es
License: MIT
Classifier: Programming Language :: Python :: 3
Classifier: License :: OSI Approved :: MIT License
Classifier: Operating System :: OS Independent
Requires-Python: >=3.9
License-File: LICENSE
Requires-Dist: numpy
Requires-Dist: requests
